{
  "ComponentIndexes": {
    "BannerUdeC": 1,
    "BannerUdeC_1": 1,
    "BannerUdeC_2": 1,
    "BannerUdeC_3": 1,
    "BannerUdeC_4": 1,
    "BannerUdeC_5": 1,
    "BannerUdeC_6": 1,
    "BannerUdeC_7": 1,
    "HeaderUdeC": 8
  },
  "ControlUniqueGuids": {},
  "ControlUniqueIds": {
    "a_d_c_e": 199,
    "a_d_c_i": 185,
    "Adjuntar_documento_extra": 82,
    "adjuntar_documento_label_1": 74,
    "adjuntar_documento_label_2": 83,
    "Adjuntar_documento_oficial": 73,
    "Adjuntar_popup_extra": 23,
    "Adjuntar_popup_oficial": 13,
    "alcance_territorial": 39,
    "alcance_territorial_convenio_solicitado": 37,
    "alcance_territorial_convenio_solicitado_1": 151,
    "ambito_de_politica": 167,
    "ambito_politica": 173,
    "App": 1,
    "Area_contribución": 179,
    "area_contribución_externa": 200,
    "area_contribución_interna": 186,
    "area_de_contribución": 182,
    "Area_de_contribución": 181,
    "Atrás": 441,
    "Atrás_1": 93,
    "Atrás_2": 482,
    "Atrás_3": 529,
    "Atrás_4": 140,
    "Atrás_5": 177,
    "Atrás_6": 233,
    "Atrás_7": 340,
    "att_registro_10_attach_extra": 28,
    "att_registro_10_attach_oficial": 18,
    "Autoridad_solicitante_2": 389,
    "BannerUdeC": 345,
    "BannerUdeC_1": 22,
    "BannerUdeC_2": 445,
    "BannerUdeC_3": 485,
    "BannerUdeC_4": 96,
    "BannerUdeC_5": 146,
    "BannerUdeC_6": 180,
    "BannerUdeC_7": 236,
    "Botones_atras_siguiente": 440,
    "Botones_atras_siguiente_1": 92,
    "Botones_atras_siguiente_2": 481,
    "Botones_atras_siguiente_3": 528,
    "Botones_atras_siguiente_4": 139,
    "Botones_atras_siguiente_5": 176,
    "Botones_atras_siguiente_6": 232,
    "Botones_atras_siguiente_7": 339,
    "btn_adjuntar_1": 81,
    "btn_adjuntar_2": 90,
    "btn_buscar_promotor": 385,
    "btn_buscar_responsable": 386,
    "btn_contraparte_in_popup_buscar": 107,
    "btn_contraparte_in_popup_cancelar": 106,
    "btn_contraparte_na_popup_buscar": 496,
    "btn_contraparte_na_popup_cancelar": 495,
    "btn_detalle_contraparte_nacional": 465,
    "btn_detalle_contraparte_nacional_1": 456,
    "btn_ods_1": 248,
    "btn_ods_10": 293,
    "btn_ods_11": 298,
    "btn_ods_12": 303,
    "btn_ods_13": 308,
    "btn_ods_14": 313,
    "btn_ods_15": 318,
    "btn_ods_16": 323,
    "btn_ods_17": 328,
    "btn_ods_2": 253,
    "btn_ods_3": 258,
    "btn_ods_4": 263,
    "btn_ods_5": 268,
    "btn_ods_6": 273,
    "btn_ods_7": 278,
    "btn_ods_8": 283,
    "btn_ods_9": 288,
    "btn_promotor_popup_buscar": 356,
    "btn_promotor_popup_cancelar": 355,
    "btn_registro_10_politica": 174,
    "btn_registro_10_popup_cancelar": 20,
    "btn_registro_10_popup_cancelar_1": 30,
    "btn_registro_10_popup_guardar": 21,
    "btn_registro_10_popup_guardar_1": 31,
    "btn_registro_11_agenda": 241,
    "btn_registro_4_e_agregar": 480,
    "btn_registro_5_popup_atras_1": 336,
    "btn_registro_5_popup_enviar": 337,
    "btn_responsable_popup_buscar": 368,
    "btn_responsable_popup_cancelar": 367,
    "buscador_a_t_input": 41,
    "buscador_n_u_s_input": 378,
    "buscar": 352,
    "buscar_1": 387,
    "buscar_2": 364,
    "buscar_3": 388,
    "buscar_4": 492,
    "buscar_5": 103,
    "Button1": 452,
    "Cargo_autoridad_2": 393,
    "cargo_autoridad_input_2": 395,
    "cargo_autoridad_label_2": 394,
    "Cargo_promotor_2": 408,
    "cargo_promotor_input_2": 411,
    "cargo_promotor_label_2": 409,
    "Cargo_responsable_2": 426,
    "cargo_responsable_input_2": 429,
    "Cargo_responsable_institucional_in": 125,
    "cargo_responsable_institucional_in_input": 127,
    "cargo_responsable_institucional_in_label": 126,
    "Cargo_responsable_institucional_na": 514,
    "cargo_responsable_institucional_na_input": 516,
    "cargo_responsable_institucional_na_label": 515,
    "cargo_responsable_label_2": 427,
    "cb_desarrollo_ambiental": 202,
    "cb_desarrollo_cultural": 217,
    "cb_desarrollo_productivo": 208,
    "cb_desarrollo_social": 214,
    "cb_educacion": 220,
    "cb_formacion_investigacion": 197,
    "cb_formacion_permanente": 191,
    "cb_formacion_postgrado": 194,
    "cb_formacion_pregrado": 188,
    "cb_inclusion": 226,
    "cb_interculturalidad": 223,
    "cb_ods_1": 245,
    "cb_ods_10": 290,
    "cb_ods_11": 295,
    "cb_ods_12": 300,
    "cb_ods_13": 305,
    "cb_ods_14": 310,
    "cb_ods_15": 315,
    "cb_ods_16": 320,
    "cb_ods_17": 325,
    "cb_ods_2": 250,
    "cb_ods_3": 255,
    "cb_ods_4": 260,
    "cb_ods_5": 265,
    "cb_ods_6": 270,
    "cb_ods_7": 275,
    "cb_ods_8": 280,
    "cb_ods_9": 285,
    "cb_ods_ninguno": 330,
    "cb_patrimonio": 211,
    "cb_salud": 229,
    "cb_sector_publico": 205,
    "cont_contraparte_internacional": 453,
    "cont_contraparte_nacional": 462,
    "cont_loading": 443,
    "cont_loading_1": 533,
    "cont_loading_2": 144,
    "cont_loading_3": 343,
    "cont_ods_1": 244,
    "cont_ods_10": 289,
    "cont_ods_11": 294,
    "cont_ods_12": 299,
    "cont_ods_13": 304,
    "cont_ods_14": 309,
    "cont_ods_15": 314,
    "cont_ods_16": 319,
    "cont_ods_17": 324,
    "cont_ods_2": 249,
    "cont_ods_3": 254,
    "cont_ods_4": 259,
    "cont_ods_5": 264,
    "cont_ods_6": 269,
    "cont_ods_7": 274,
    "cont_ods_8": 279,
    "cont_ods_9": 284,
    "cont_ods_ninguno": 329,
    "cont_vacio_in": 475,
    "cont_vacio_na": 471,
    "Contenedor_a_d_c": 183,
    "Contenedor_a_d_p": 166,
    "Contenedor_a_t": 38,
    "Contenedor_c_d_s": 242,
    "Contenedor_c_d_t": 152,
    "Contenedor_casilla": 187,
    "Contenedor_casilla_1": 193,
    "Contenedor_casilla_10": 204,
    "Contenedor_casilla_11": 210,
    "Contenedor_casilla_12": 216,
    "Contenedor_casilla_13": 222,
    "Contenedor_casilla_2": 196,
    "Contenedor_casilla_3": 190,
    "Contenedor_casilla_4": 201,
    "Contenedor_casilla_5": 207,
    "Contenedor_casilla_6": 213,
    "Contenedor_casilla_7": 219,
    "Contenedor_casilla_8": 225,
    "Contenedor_casilla_9": 228,
    "Contenedor_d_c_s": 34,
    "Contenedor_d_e_c_in": 111,
    "Contenedor_d_e_c_na": 500,
    "Contenedor_d_i_c": 149,
    "Contenedor_d_u_s_op3": 371,
    "Contenedor_datos_convenio": 32,
    "Contenedor_e_c": 448,
    "Contenedor_m_c": 60,
    "Contenedor_s_d_p": 159,
    "Contenedor_seleccionable": 62,
    "Contenedor_seleccionable_1": 40,
    "Contenedor_seleccionable_4": 376,
    "Contenedor_seleccionable_5": 154,
    "Contenedor_seleccionable_6": 169,
    "Contenedor_seleccionable_7": 161,
    "Contenedor_seleccionable_tipo_solicitud": 55,
    "Contenedor_seleccionable_tipología": 48,
    "Contenedor_t_c": 46,
    "Contenedor_t_s": 53,
    "contraparte_internacional_popup": 97,
    "contraparte_nacional_popup": 486,
    "contribución_al_desarrollo": 240,
    "Contribución_al_desarrollo": 239,
    "Contribución_desarrollo": 235,
    "convenio_de_tipo": 153,
    "convenio_tipo": 158,
    "Correo_autoridad_2": 396,
    "correo_autoridad_input_2": 398,
    "correo_autoridad_label_2": 397,
    "correo_electronico_in": 132,
    "correo_electronico_in_input": 134,
    "correo_electronico_in_label": 133,
    "correo_electronico_na": 521,
    "correo_electronico_na_input": 523,
    "correo_electronico_na_label": 522,
    "Correo_promotor_2": 412,
    "correo_promotor_input_2": 415,
    "correo_promotor_label_2": 413,
    "Correo_responsable_2": 430,
    "correo_responsable_input_2": 433,
    "correo_responsable_label_2": 431,
    "Datos_contraparte_internacional": 95,
    "Datos_contraparte_nacional": 484,
    "Datos_convenio": 12,
    "datos_convenio_solicitado": 33,
    "datos_de_la_unidad_1": 382,
    "datos_del_promotor_1": 383,
    "datos_del_responsable_1": 384,
    "datos_entidad_contraparte_in": 110,
    "Datos_entidad_contraparte_in": 109,
    "datos_entidad_contraparte_na": 499,
    "Datos_entidad_contraparte_na": 498,
    "datos_info_convenio": 148,
    "Datos_unidad_solicitante": 369,
    "datos_unidad_solicitante_3": 370,
    "descripcion_proposito_1": 70,
    "documentacion": 72,
    "Documentacion": 71,
    "Eliminar": 530,
    "Eliminar_1": 141,
    "Entidad_contraparte": 444,
    "entidades_contraparte": 447,
    "Entidades_contraparte": 446,
    "Especificaciones_convenio": 36,
    "fig_background_perfil": 7,
    "fig_contraparte_arrow": 470,
    "fig_contraparte_arrow_1": 461,
    "fig_registro_10_popup_bg": 14,
    "fig_registro_10_popup_bg_1": 24,
    "fig_registro_5_bg": 357,
    "fig_registro_5_bg_1": 497,
    "fig_registro_5_bg_2": 108,
    "fig_registro_5_bg_3": 238,
    "fig_registro_5_popup_bg": 347,
    "fig_registro_5_popup_bg_1": 359,
    "fig_registro_5_popup_bg_2": 487,
    "fig_registro_5_popup_bg_3": 98,
    "fig_registro_5_popup_bg_4": 237,
    "fondo_blanco": 348,
    "fondo_blanco_1": 35,
    "fondo_blanco_10": 184,
    "fondo_blanco_11": 372,
    "fondo_blanco_12": 243,
    "fondo_blanco_3": 360,
    "fondo_blanco_4": 488,
    "fondo_blanco_5": 449,
    "fondo_blanco_6": 501,
    "fondo_blanco_7": 112,
    "fondo_blanco_8": 99,
    "fondo_blanco_9": 150,
    "fondo_celeste": 63,
    "fondo_celeste_1": 49,
    "fondo_celeste_10": 170,
    "fondo_celeste_11": 162,
    "fondo_celeste_2": 42,
    "fondo_celeste_3": 56,
    "fondo_celeste_8": 377,
    "fondo_celeste_9": 156,
    "fondo_registro_1": 76,
    "fondo_registro_2": 85,
    "gal_contraparte_internacional": 454,
    "gal_contraparte_nacional": 463,
    "gal_tabs": 450,
    "Gallery1_1": 77,
    "Gallery1_2": 86,
    "galleryTemplate1_1": 78,
    "galleryTemplate1_2": 464,
    "galleryTemplate1_3": 87,
    "galleryTemplate1_4": 455,
    "galleryTemplate2": 451,
    "grp_registro_5_popup_1": 342,
    "Guardar": 532,
    "Guardar_1": 143,
    "HeaderUdeC": 4,
    "Host": 3,
    "icon_tabs_contenido_separador": 479,
    "Image1": 472,
    "Image1_1": 476,
    "img_arrow_contraparte_nacional": 468,
    "img_arrow_contraparte_nacional_1": 459,
    "img_contraparte": 467,
    "img_contraparte_1": 458,
    "img_info_ods_1": 247,
    "img_info_ods_10": 292,
    "img_info_ods_11": 297,
    "img_info_ods_12": 302,
    "img_info_ods_13": 307,
    "img_info_ods_14": 312,
    "img_info_ods_15": 317,
    "img_info_ods_16": 322,
    "img_info_ods_17": 327,
    "img_info_ods_2": 252,
    "img_info_ods_3": 257,
    "img_info_ods_4": 262,
    "img_info_ods_5": 267,
    "img_info_ods_6": 272,
    "img_info_ods_7": 277,
    "img_info_ods_8": 282,
    "img_info_ods_9": 287,
    "img_loading": 438,
    "img_loading_1": 525,
    "img_loading_2": 136,
    "img_loading_3": 334,
    "img_logo_udec": 9,
    "img_ods_1": 246,
    "img_ods_10": 291,
    "img_ods_11": 296,
    "img_ods_12": 301,
    "img_ods_13": 306,
    "img_ods_14": 311,
    "img_ods_15": 316,
    "img_ods_16": 321,
    "img_ods_17": 326,
    "img_ods_18": 331,
    "img_ods_2": 251,
    "img_ods_3": 256,
    "img_ods_4": 261,
    "img_ods_5": 266,
    "img_ods_6": 271,
    "img_ods_7": 276,
    "img_ods_8": 281,
    "img_ods_9": 286,
    "img_perfil": 8,
    "img_registro_10_popup": 17,
    "img_registro_10_popup_1": 27,
    "img_registro_10_popup_bg": 15,
    "img_registro_10_popup_bg_1": 25,
    "img_registro_5_popup_bg_1": 332,
    "img_subir_1": 80,
    "img_subir_2": 89,
    "Información_convenio": 145,
    "Información_de_convenio": 147,
    "inp_contraparte_in_popup_search": 102,
    "inp_contraparte_na_popup_search": 491,
    "inp_promotor_popup_search": 351,
    "inp_responsable_popup_search": 363,
    "lbl_bienvenido": 6,
    "lbl_contraparte_in_popup_faltandatos": 104,
    "lbl_contraparte_in_popup_noencontrado": 105,
    "lbl_contraparte_in_popup_rut": 101,
    "lbl_contraparte_in_popup_titulo": 100,
    "lbl_contraparte_na_popup_faltandatos": 493,
    "lbl_contraparte_na_popup_noencontrado": 494,
    "lbl_contraparte_na_popup_rut": 490,
    "lbl_contraparte_na_popup_titulo": 489,
    "lbl_contraparte_nacional_nombre": 466,
    "lbl_contraparte_nacional_nombre_1": 457,
    "lbl_contraparte_nacional_rut": 469,
    "lbl_contraparte_nacional_rut_1": 460,
    "lbl_educacion": 221,
    "lbl_falta_correo": 526,
    "lbl_falta_correo_1": 137,
    "lbl_faltan_datos": 439,
    "lbl_faltan_datos_1": 91,
    "lbl_faltan_datos_2": 527,
    "lbl_faltan_datos_3": 138,
    "lbl_faltan_datos_4": 175,
    "lbl_faltan_datos_5": 231,
    "lbl_faltan_datos_6": 338,
    "lbl_nombre_usuario": 10,
    "lbl_promotor_popup_correo": 350,
    "lbl_promotor_popup_faltandatos": 353,
    "lbl_promotor_popup_noencontrado": 354,
    "lbl_promotor_popup_titulo": 349,
    "lbl_registro_10_faltandatos_1": 19,
    "lbl_registro_10_faltandatos_2": 29,
    "lbl_registro_10_popup_titulo": 16,
    "lbl_registro_10_popup_titulo_1": 26,
    "lbl_registro_9_desarrollo_ambiental": 203,
    "lbl_registro_9_desarrollo_cultural": 218,
    "lbl_registro_9_desarrollo_productivo": 209,
    "lbl_registro_9_desarrollo_social": 215,
    "lbl_registro_9_formacion_permanente": 192,
    "lbl_registro_9_formacion_postgrado": 195,
    "lbl_registro_9_formacion_pregrado": 189,
    "lbl_registro_9_inclusion": 227,
    "lbl_registro_9_interculturalidad": 224,
    "lbl_registro_9_investigacion": 198,
    "lbl_registro_9_patrimonio": 212,
    "lbl_registro_9_salud": 230,
    "lbl_registro_9_sector_publico": 206,
    "lbl_registro_popup_5_correo_1": 335,
    "lbl_registro_popup_5_titulo_1": 333,
    "lbl_responsable_popup_correo": 362,
    "lbl_responsable_popup_faltandatos": 365,
    "lbl_responsable_popup_noencontrado": 366,
    "lbl_responsable_popup_titulo": 361,
    "lbl_subtitulo": 11,
    "lbl_titulo": 5,
    "modalidades": 61,
    "no_contraparte_in_lb": 478,
    "no_contraparte_na_lb": 474,
    "Nombre_autoridad_2": 390,
    "nombre_autoridad_solicitante_input_2": 392,
    "nombre_autoridad_solicitante_label_2": 391,
    "Nombre_promotor_2": 404,
    "nombre_promotor_input_2": 407,
    "nombre_promotor_label_2": 405,
    "Nombre_representante_legal_in": 116,
    "nombre_representante_legal_in_input": 118,
    "nombre_representante_legal_in_label": 117,
    "Nombre_representante_legal_na": 505,
    "nombre_representante_legal_na_input": 507,
    "nombre_representante_legal_na_label": 506,
    "Nombre_responsable_2": 422,
    "nombre_responsable_input_2": 425,
    "Nombre_responsable_institucional_in": 121,
    "nombre_responsable_institucional_in_input": 123,
    "nombre_responsable_institucional_in_label": 122,
    "Nombre_responsable_institucional_na": 510,
    "nombre_responsable_institucional_na_input": 512,
    "nombre_responsable_institucional_na_label": 511,
    "nombre_responsable_label_2": 423,
    "Nombre_unidad_contraparte_in": 113,
    "nombre_unidad_contraparte_in_input": 115,
    "nombre_unidad_contraparte_in_label": 114,
    "Nombre_unidad_contraparte_na": 502,
    "nombre_unidad_contraparte_na_input": 504,
    "nombre_unidad_contraparte_na_label": 503,
    "nombre_unidad_input": 375,
    "nombre_unidad_input_3": 168,
    "nombre_unidad_label_2": 374,
    "nombre_unidad_solicitante": 381,
    "Nombre_unidad_solicitante_2": 373,
    "pais_in": 129,
    "pais_in_input": 131,
    "pais_in_label": 130,
    "pais_na": 518,
    "pais_na_input": 520,
    "pais_na_label": 519,
    "promotor_popup": 346,
    "Promotor_unidad_2": 403,
    "Promotor_unidad_solicitante_in": 120,
    "Promotor_unidad_solicitante_na": 509,
    "Propósito": 67,
    "propósito_central": 68,
    "Responsable_institucional_2": 421,
    "responsable_popup": 358,
    "sector_de_politica": 160,
    "sector_politica": 165,
    "separador": 402,
    "separador_1": 420,
    "Siguiente": 442,
    "Siguiente_1": 94,
    "Siguiente_2": 483,
    "Siguiente_3": 531,
    "Siguiente_4": 142,
    "Siguiente_5": 178,
    "Siguiente_6": 234,
    "Siguiente_7": 341,
    "sin_alcance_territorial": 44,
    "sin_ambito_politica": 171,
    "sin_cargo": 517,
    "sin_cargo_in": 128,
    "sin_cargo_promotor_1": 410,
    "sin_cargo_responsable": 428,
    "sin_contraparte_in_lb": 477,
    "sin_contraparte_na_lb": 473,
    "sin_convenio_tipo": 155,
    "sin_correo_in": 135,
    "sin_correo_na": 524,
    "sin_correo_promotor": 414,
    "sin_correo_responsable": 432,
    "sin_documento_extra": 84,
    "sin_documento_oficial": 75,
    "sin_modalidad": 65,
    "sin_nombre_promotor": 406,
    "sin_nombre_representante_legal": 508,
    "sin_nombre_representante_legal_in": 119,
    "sin_nombre_responsable": 424,
    "sin_nombre_responsable_institucional": 513,
    "sin_nombre_responsable_institucional_in": 124,
    "sin_nombre_unidad": 380,
    "sin_proposito_central": 69,
    "sin_sector_politica": 164,
    "sin_solicitud": 58,
    "sin_telefono_promotor": 418,
    "sin_telefono_responsable": 436,
    "sin_tipologia": 51,
    "solicitud": 54,
    "tapar_ambito_politica": 172,
    "tapar_convenio_tipo": 157,
    "tapar_convenio_tipo_1": 163,
    "tapar_nombre_unidad_solicitante": 379,
    "tapar_tipo_alcance": 43,
    "tapar_tipo_modalidades": 64,
    "tapar_tipo_solicitud": 57,
    "tapar_tipo_tipologia": 50,
    "Telefono_autoridad_2": 399,
    "telefono_autoridad_input_2": 401,
    "telefono_autoridad_label_2": 400,
    "Telefono_promotor_2": 416,
    "telefono_promotor_input_2": 419,
    "telefono_promotor_label_2": 417,
    "Telefono_responsable_2": 434,
    "telefono_responsable_input_2": 437,
    "telefono_responsable_label_2": 435,
    "tipo_alcance": 45,
    "tipo_modalidades": 66,
    "tipo_solicitud": 59,
    "tipo_tipologia": 52,
    "tipologia": 47,
    "Title1_1": 79,
    "Title1_2": 88,
    "Unidad_solicitante": 344
  },
  "FunctionParamsInvariantScripts": {},
  "FunctionParamsInvariantScriptsOnInstances": {},
  "HeaderLastSavedDateTimeUTC": "05/02/2023 16:25:55",
  "IsLegacyComponentAllowGlobalScopeCase": false,
  "LocalConnectionIDReferences": {
    "02917942-c1e0-4f4a-a81e-14cdfcf4bcd1": "\"/providers/microsoft.powerapps/apis/shared_logicflows/connections/993e652b7390bd63fd075c5e46bc045e-a174438b0269b008\"",
    "4b4168bc-54db-494d-a3a1-b483ed914a76": "\"/providers/microsoft.powerapps/apis/shared_logicflows/connections/9cf61b6ed16ce60590816a787ee95a53-a174438b0269b008\"",
    "8789f143-b674-49d3-99ce-85bcaafed327": "\"/providers/microsoft.powerapps/apis/shared_logicflows/connections/5b4f687e3ccb5846d6949e769283dc36-a174438b0269b008\"",
    "97ce6c13-ada6-45c3-b045-e9802f207fbe": "\"/providers/microsoft.powerapps/apis/shared_logicflows/connections/cad1d9397b72360f5f897ec4a8a79c50-a174438b0269b008\"",
    "ac5ecc92-f9ac-49a5-9e57-94552f4ccb96": "\"/providers/microsoft.powerapps/apis/shared_logicflows/connections/8f6c6c4578cb7df596935b15dc0ad34b-a174438b0269b008\"",
    "b2390245-ea50-4ac2-943d-8edf576a5147": "\"/providers/microsoft.powerapps/apis/shared_sharepointonline/connections/1765ce16774d43bf908c5ff9427a0791\"",
    "bd7cd86a-a6c9-4c76-9a35-563e3da2372b": "\"/providers/microsoft.powerapps/apis/shared_logicflows/connections/e646ba122429497ab8931a1dfc24266b\"",
    "c8c7ef2c-b970-414a-b7c0-1e77275b1c3c": "\"/providers/microsoft.powerapps/apis/shared_logicflows/connections/996b7d298f96098144b8a7cfa3d7c136-a174438b0269b008\"",
    "d7aaf4a1-bfd3-474c-8f13-3fdc192d1739": "\"/providers/microsoft.powerapps/apis/shared_logicflows/connections/158579e55918e59805b1dbf7f8de7e69-a174438b0269b008\""
  },
  "LocalDatabaseReferencesAsEmpty": false,
  "LocalResourceFileNames": {
    "0": "c328676b-c82a-4985-8591-85fe26f75532.png",
    "1": "cae73ef9-9c9c-493f-8488-63d8417c0f70.png",
    "10": "ddd55a13-7c81-4d54-8123-5f53f0f38713.png",
    "11": "b823b62f-7c20-4124-ae9c-cccc68f88aa9.png",
    "12": "6196cca9-1d02-4ee0-997d-7e92b3751dce.png",
    "13": "ec04a139-6ae5-43c4-914f-e832b2f8ac09.png",
    "14": "b5550807-0224-4f12-aedd-bace3c95642f.png",
    "15": "b5220a9c-c9e8-4958-bc4d-241750d76cba.png",
    "16": "be12d911-52f6-4427-8e5a-7aafc469f9f2.png",
    "17": "aec32540-1656-4bd6-97c9-4ace2de3c74b.png",
    "2": "6cf302cc-8dab-4a5a-9b3b-4c8716178f29.png",
    "3": "5396ae33-a7d2-41f8-af36-6bef978c7c92.png",
    "4": "cde55036-d4bd-47cf-8985-b89227393490.png",
    "5": "80151fc0-4298-4173-b85e-40fab561c3bc.png",
    "6": "18f2f3ae-9292-4f98-8ffb-237fa5375b45.png",
    "7": "94a0529c-9abb-41c3-893f-25e45b8fe41c.png",
    "8": "26bead31-688b-4b75-962f-4d7ee55a5b21.png",
    "9": "ca3bb2ec-ee7b-4a71-bbf6-351ad9ed1e65.png",
    "attach": "0a45afcf-7927-4564-b4a0-def21e0c89a6.png",
    "background-input": "9035e58f-dc8d-48ff-ad86-4215130b9d71.png",
    "background-section": "7641f5fc-19a6-4e38-9001-413f748841fc.png",
    "fondo_deshabilitado": "f3760a10-3a9a-4d48-9799-9225e9a6d9b3.jpg",
    "group-2-copy": "4123f990-cfa9-4918-8897-75905d6ff305.png",
    "ico_arrow": "769738be-faad-43e7-a773-ef0094e9ed52.png",
    "ico_search": "a2f8145b-0d3d-4193-b24d-b28b3404c43f.png",
    "informacion": "109a4d68-c715-4081-825d-572633ca19a5.png",
    "loading": "d8ca3439-f9bf-40e1-b9b3-89f74ad115f0.gif",
    "logo-udec": "65c83c79-3ee6-43ce-993b-d0f32a8abe15.png",
    "upload": "4ed892f9-8479-48f0-ad2d-5df68b201125.png",
    "vacio": "66766a0b-e8e7-415f-afd9-5e303142cf2c.png"
  },
  "LocalResourceRootPaths": {
    "0": "https://docserverpwaprodeus.blob.core.windows.net/a1ad3cc1-5892-4ab4-b451-3540e02220e9-1/resource/Assets0Images0c328676b-c82a-4985-8591-85fe26f75532.png?sv=2018-03-28&sr=b&sig=2O9L%2Fusl%2BneuF0Snr62z5oBUv8CPfKIAJ5LExOerg5k%3D&spr=https&se=2023-05-03T16%3A33%3A34Z&sp=r",
    "1": "https://docserverpwaprodeus.blob.core.windows.net/a1ad3cc1-5892-4ab4-b451-3540e02220e9-1/resource/Assets0Images0cae73ef9-9c9c-493f-8488-63d8417c0f70.png?sv=2018-03-28&sr=b&sig=J1vLwWTl5GNZlKxLklBRELdmjUaq7DekkQgXX8aRDDA%3D&spr=https&se=2023-05-03T16%3A33%3A34Z&sp=r",
    "10": "https://docserverpwaprodeus.blob.core.windows.net/a1ad3cc1-5892-4ab4-b451-3540e02220e9-1/resource/Assets0Images0ddd55a13-7c81-4d54-8123-5f53f0f38713.png?sv=2018-03-28&sr=b&sig=a%2F19y4oR96AQBcVS1fg%2BWpHJtbyJVDa6KIsiTq0qpbw%3D&spr=https&se=2023-05-03T16%3A33%3A34Z&sp=r",
    "11": "https://docserverpwaprodeus.blob.core.windows.net/a1ad3cc1-5892-4ab4-b451-3540e02220e9-1/resource/Assets0Images0b823b62f-7c20-4124-ae9c-cccc68f88aa9.png?sv=2018-03-28&sr=b&sig=1eyT5AG02u3w%2FY%2B2atDbeKKRTvrLldJMoUeksWa6t0w%3D&spr=https&se=2023-05-03T16%3A33%3A34Z&sp=r",
    "12": "https://docserverpwaprodeus.blob.core.windows.net/a1ad3cc1-5892-4ab4-b451-3540e02220e9-1/resource/Assets0Images06196cca9-1d02-4ee0-997d-7e92b3751dce.png?sv=2018-03-28&sr=b&sig=4IjZzOxJJ59W5ohBXYssoS6njG4xssl8HWDaL51y%2FP0%3D&spr=https&se=2023-05-03T16%3A33%3A34Z&sp=r",
    "13": "https://docserverpwaprodeus.blob.core.windows.net/a1ad3cc1-5892-4ab4-b451-3540e02220e9-1/resource/Assets0Images0ec04a139-6ae5-43c4-914f-e832b2f8ac09.png?sv=2018-03-28&sr=b&sig=zw4uToff%2BEQmLkH7joCN3BArrJcbjajCgd%2BDO9G8%2FV4%3D&spr=https&se=2023-05-03T16%3A33%3A34Z&sp=r",
    "14": "https://docserverpwaprodeus.blob.core.windows.net/a1ad3cc1-5892-4ab4-b451-3540e02220e9-1/resource/Assets0Images0b5550807-0224-4f12-aedd-bace3c95642f.png?sv=2018-03-28&sr=b&sig=0jeBB5xte9vv0Od5GJn5ALl5vLDDiuG%2FpOi7SuiiIWs%3D&spr=https&se=2023-05-03T16%3A33%3A34Z&sp=r",
    "15": "https://docserverpwaprodeus.blob.core.windows.net/a1ad3cc1-5892-4ab4-b451-3540e02220e9-1/resource/Assets0Images0b5220a9c-c9e8-4958-bc4d-241750d76cba.png?sv=2018-03-28&sr=b&sig=ijhrx4hPoxDq1GxmGrN2kHeOMoAJAXNjN%2FDDZi0CS6U%3D&spr=https&se=2023-05-03T16%3A33%3A34Z&sp=r",
    "16": "https://docserverpwaprodeus.blob.core.windows.net/a1ad3cc1-5892-4ab4-b451-3540e02220e9-1/resource/Assets0Images0be12d911-52f6-4427-8e5a-7aafc469f9f2.png?sv=2018-03-28&sr=b&sig=8wbxQ38cXZ6oAJ2PvWGkLxp0sCUPSfqd4DMR0uQG%2B%2Fo%3D&spr=https&se=2023-05-03T16%3A33%3A34Z&sp=r",
    "17": "https://docserverpwaprodeus.blob.core.windows.net/a1ad3cc1-5892-4ab4-b451-3540e02220e9-1/resource/Assets0Images0aec32540-1656-4bd6-97c9-4ace2de3c74b.png?sv=2018-03-28&sr=b&sig=JYDd28EAtxdH1fnV6lUTVlDnA32zox5Qk8zc%2Beqe3aE%3D&spr=https&se=2023-05-03T16%3A33%3A34Z&sp=r",
    "2": "https://docserverpwaprodeus.blob.core.windows.net/a1ad3cc1-5892-4ab4-b451-3540e02220e9-1/resource/Assets0Images06cf302cc-8dab-4a5a-9b3b-4c8716178f29.png?sv=2018-03-28&sr=b&sig=AmbasWeHxarOaqTS58YUWcyOPXw2KM13D48U42AaFfE%3D&spr=https&se=2023-05-03T16%3A33%3A34Z&sp=r",
    "3": "https://docserverpwaprodeus.blob.core.windows.net/a1ad3cc1-5892-4ab4-b451-3540e02220e9-1/resource/Assets0Images05396ae33-a7d2-41f8-af36-6bef978c7c92.png?sv=2018-03-28&sr=b&sig=6n4yGwcqcQ4Pj5YCGtssjcNOF00ODYHjL5t8yyRL8Us%3D&spr=https&se=2023-05-03T16%3A33%3A34Z&sp=r",
    "4": "https://docserverpwaprodeus.blob.core.windows.net/a1ad3cc1-5892-4ab4-b451-3540e02220e9-1/resource/Assets0Images0cde55036-d4bd-47cf-8985-b89227393490.png?sv=2018-03-28&sr=b&sig=FngvL1oSgNPFkQ04dzqJDYi5GTCAuQy6QPIjusJxXAQ%3D&spr=https&se=2023-05-03T16%3A33%3A34Z&sp=r",
    "5": "https://docserverpwaprodeus.blob.core.windows.net/a1ad3cc1-5892-4ab4-b451-3540e02220e9-1/resource/Assets0Images080151fc0-4298-4173-b85e-40fab561c3bc.png?sv=2018-03-28&sr=b&sig=VUXDIyM05KROC%2BMfM0VaPqpjNg83e0Ohi8EaEGLd6RQ%3D&spr=https&se=2023-05-03T16%3A33%3A34Z&sp=r",
    "6": "https://docserverpwaprodeus.blob.core.windows.net/a1ad3cc1-5892-4ab4-b451-3540e02220e9-1/resource/Assets0Images018f2f3ae-9292-4f98-8ffb-237fa5375b45.png?sv=2018-03-28&sr=b&sig=Jxy8uoWuKzqCzXoETFKtYIkwNNzLlVpMxRW4HDqNLyo%3D&spr=https&se=2023-05-03T16%3A33%3A34Z&sp=r",
    "7": "https://docserverpwaprodeus.blob.core.windows.net/a1ad3cc1-5892-4ab4-b451-3540e02220e9-1/resource/Assets0Images094a0529c-9abb-41c3-893f-25e45b8fe41c.png?sv=2018-03-28&sr=b&sig=nDltt8QknxaByCqbG31eimPxfOJSMcrM7R%2BSS2S0%2BSw%3D&spr=https&se=2023-05-03T16%3A33%3A34Z&sp=r",
    "8": "https://docserverpwaprodeus.blob.core.windows.net/a1ad3cc1-5892-4ab4-b451-3540e02220e9-1/resource/Assets0Images026bead31-688b-4b75-962f-4d7ee55a5b21.png?sv=2018-03-28&sr=b&sig=E16emAMIDoQc6%2FG%2B%2B%2BQu2U26FBm6JWB7PNIHpwvNDec%3D&spr=https&se=2023-05-03T16%3A33%3A34Z&sp=r",
    "9": "https://docserverpwaprodeus.blob.core.windows.net/a1ad3cc1-5892-4ab4-b451-3540e02220e9-1/resource/Assets0Images0ca3bb2ec-ee7b-4a71-bbf6-351ad9ed1e65.png?sv=2018-03-28&sr=b&sig=CHNynv89I8cFONw6puQZB%2BfIwO4jHzt86nCzFqhXToM%3D&spr=https&se=2023-05-03T16%3A33%3A34Z&sp=r",
    "attach": "https://docserverpwaprodeus.blob.core.windows.net/a1ad3cc1-5892-4ab4-b451-3540e02220e9-1/resource/Assets0Images00a45afcf-7927-4564-b4a0-def21e0c89a6.png?sv=2018-03-28&sr=b&sig=ulSWDRfJcx%2Bsc8EK7eqmt1wXxG3GOvRgDs1eXNmE9fk%3D&spr=https&se=2023-05-03T16%3A33%3A34Z&sp=r",
    "background-input": "https://docserverpwaprodeus.blob.core.windows.net/a1ad3cc1-5892-4ab4-b451-3540e02220e9-1/resource/Assets0Images09035e58f-dc8d-48ff-ad86-4215130b9d71.png?sv=2018-03-28&sr=b&sig=IBi%2FTULy2hZYyuVMddqedy8%2B0ITHhviKYjCAnkPM4mo%3D&spr=https&se=2023-05-03T16%3A33%3A34Z&sp=r",
    "background-section": "https://docserverpwaprodeus.blob.core.windows.net/a1ad3cc1-5892-4ab4-b451-3540e02220e9-1/resource/Assets0Images07641f5fc-19a6-4e38-9001-413f748841fc.png?sv=2018-03-28&sr=b&sig=fRPND1SHkHRNpSHPxHWPKPy2fS7%2B2g171s00Wi1QurA%3D&spr=https&se=2023-05-03T16%3A33%3A34Z&sp=r",
    "fondo_deshabilitado": "https://docserverpwaprodeus.blob.core.windows.net/a1ad3cc1-5892-4ab4-b451-3540e02220e9-1/resource/Assets0Images0f3760a10-3a9a-4d48-9799-9225e9a6d9b3.jpg?sv=2018-03-28&sr=b&sig=PldCHs6ZH%2BtddYjvfA8kSZflFHBRxh2UPRl%2B3gpa3Rw%3D&spr=https&se=2023-05-03T16%3A33%3A34Z&sp=r",
    "group-2-copy": "https://docserverpwaprodeus.blob.core.windows.net/a1ad3cc1-5892-4ab4-b451-3540e02220e9-1/resource/Assets0Images04123f990-cfa9-4918-8897-75905d6ff305.png?sv=2018-03-28&sr=b&sig=%2BjxonYZzNiG%2FkdwW04EbQuhldHdluyj7p1sRv5uo0CY%3D&spr=https&se=2023-05-03T16%3A33%3A34Z&sp=r",
    "ico_arrow": "https://docserverpwaprodeus.blob.core.windows.net/a1ad3cc1-5892-4ab4-b451-3540e02220e9-1/resource/Assets0Images0769738be-faad-43e7-a773-ef0094e9ed52.png?sv=2018-03-28&sr=b&sig=pivPtwfXNO1RU92twytEo8ciN8FWxZMdFdYjqHqVPsI%3D&spr=https&se=2023-05-03T16%3A33%3A34Z&sp=r",
    "ico_search": "https://docserverpwaprodeus.blob.core.windows.net/a1ad3cc1-5892-4ab4-b451-3540e02220e9-1/resource/Assets0Images0a2f8145b-0d3d-4193-b24d-b28b3404c43f.png?sv=2018-03-28&sr=b&sig=EfnWLkfZ1X%2FcZgKeH1NTYEqimImEQEeifjISHsrkTHo%3D&spr=https&se=2023-05-03T16%3A33%3A34Z&sp=r",
    "informacion": "https://docserverpwaprodeus.blob.core.windows.net/a1ad3cc1-5892-4ab4-b451-3540e02220e9-1/resource/Assets0Images0109a4d68-c715-4081-825d-572633ca19a5.png?sv=2018-03-28&sr=b&sig=Wmabt5%2FkohGdL1PWsq2JRoeTDQZXgDmQ6PWmpJ4ypUs%3D&spr=https&se=2023-05-03T16%3A33%3A34Z&sp=r",
    "loading": "https://docserverpwaprodeus.blob.core.windows.net/a1ad3cc1-5892-4ab4-b451-3540e02220e9-1/resource/Assets0Images0d8ca3439-f9bf-40e1-b9b3-89f74ad115f0.gif?sv=2018-03-28&sr=b&sig=xG19P1TMWIw%2FQZhfpOzDt1NJnQhXRLD8DCLk4B8aItY%3D&spr=https&se=2023-05-03T16%3A33%3A34Z&sp=r",
    "logo-udec": "https://docserverpwaprodeus.blob.core.windows.net/a1ad3cc1-5892-4ab4-b451-3540e02220e9-1/resource/Assets0Images065c83c79-3ee6-43ce-993b-d0f32a8abe15.png?sv=2018-03-28&sr=b&sig=HK5sbNh8JoWaVIknT1mP2vtXApkdW2urHqo6omGNm%2BY%3D&spr=https&se=2023-05-03T16%3A33%3A34Z&sp=r",
    "upload": "https://docserverpwaprodeus.blob.core.windows.net/a1ad3cc1-5892-4ab4-b451-3540e02220e9-1/resource/Assets0Images04ed892f9-8479-48f0-ad2d-5df68b201125.png?sv=2018-03-28&sr=b&sig=ZEhY%2FYpQdXoByMGVOnkX0%2FzuiZ21dcJhA9Xo7kTQu8M%3D&spr=https&se=2023-05-03T16%3A33%3A34Z&sp=r",
    "vacio": "https://docserverpwaprodeus.blob.core.windows.net/a1ad3cc1-5892-4ab4-b451-3540e02220e9-1/resource/Assets0Images066766a0b-e8e7-415f-afd9-5e303142cf2c.png?sv=2018-03-28&sr=b&sig=K%2FipBlmfIrPSdWWW15MEqTacBGCUYi3M%2BT%2F%2BYYjeXhM%3D&spr=https&se=2023-05-03T16%3A33%3A34Z&sp=r"
  },
  "OrderComponentMetadata": {
    "561f66e7d0a2482e9212edb43132f4a8": 0
  },
  "OrderComponentTemplate": {
    "561f66e7d0a2482e9212edb43132f4a8": 0
  },
  "OrderDataSource": {
    "Almacenamientoarchivosensharepoint": 7,
    "contrapartes_internacionales": 12,
    "contrapartes_nacionales": 11,
    "contrib_externa_checkboxes": 20,
    "contrib_interna_checkboxes": 19,
    "CustomGallerySample": 10,
    "datos": 17,
    "datos_contribucion_externa": 25,
    "datos_contribucion_interna": 26,
    "datos_ods_cargados": 27,
    "datosArea_contribucion": 21,
    "datosContribucion_desarrollo": 23,
    "documentos_cargados": 24,
    "DropDownSample": 9,
    "DTI-PAAgregarsolicituddeconvenio": 6,
    "DTI-PATraeinstituciónnacional": 5,
    "DTI-PATraerinstitucióninternacional": 4,
    "lista_alcance": 16,
    "lista_modalidad": 13,
    "lista_tipo_solicitud": 14,
    "lista_tipologia": 15,
    "Listaespecificacionesconvenio": 1,
    "ods_checkboxes": 22,
    "organismos_actividad": 18,
    "RadioSample": 8,
    "VRIM-PA-Traeaprobadordetrabajador": 3,
    "VRIM-PATraedatosdeusuario": 0,
    "VRIM-PATraelistadoactividades": 2
  },
  "OrderGroupControls": {
    "cont_loading": {
      "fig_registro_5_bg": 1,
      "img_loading": 0
    },
    "cont_loading_1": {
      "fig_registro_5_bg_1": 1,
      "img_loading_1": 0
    },
    "cont_loading_2": {
      "fig_registro_5_bg_2": 1,
      "img_loading_2": 0
    },
    "cont_loading_3": {
      "fig_registro_5_bg_3": 1,
      "img_loading_3": 0
    },
    "grp_registro_5_popup_1": {
      "btn_registro_5_popup_atras_1": 0,
      "btn_registro_5_popup_enviar": 1,
      "fig_registro_5_popup_bg_4": 5,
      "img_registro_5_popup_bg_1": 4,
      "lbl_registro_popup_5_correo_1": 2,
      "lbl_registro_popup_5_titulo_1": 3
    }
  },
  "OrderPcfTemplate": {},
  "OrderTemplate": {},
  "OrderXMLTemplate": {
    "attachments": 4,
    "button": 5,
    "checkbox": 10,
    "circle": 6,
    "dropdown": 8,
    "gallery": 9,
    "groupContainer": 0,
    "icon": 11,
    "image": 2,
    "label": 3,
    "rectangle": 1,
    "text": 7
  },
  "OverridablePropertiesEntry": {
    "a_d_c_e": {},
    "a_d_c_i": {},
    "Adjuntar_documento_extra": {},
    "adjuntar_documento_label_1": {},
    "adjuntar_documento_label_2": {},
    "Adjuntar_documento_oficial": {},
    "Adjuntar_popup_extra": {},
    "Adjuntar_popup_oficial": {},
    "alcance_territorial": {},
    "alcance_territorial_convenio_solicitado": {},
    "alcance_territorial_convenio_solicitado_1": {},
    "ambito_de_politica": {},
    "ambito_politica": {},
    "App": {},
    "Area_contribución": {},
    "area_contribución_externa": {},
    "area_contribución_interna": {},
    "area_de_contribución": {},
    "Area_de_contribución": {},
    "Atrás": {},
    "Atrás_1": {},
    "Atrás_2": {},
    "Atrás_3": {},
    "Atrás_4": {},
    "Atrás_5": {},
    "Atrás_6": {},
    "Atrás_7": {},
    "att_registro_10_attach_extra": {},
    "att_registro_10_attach_oficial": {},
    "Autoridad_solicitante_2": {},
    "BannerUdeC": {},
    "BannerUdeC_1": {},
    "BannerUdeC_2": {},
    "BannerUdeC_3": {},
    "BannerUdeC_4": {},
    "BannerUdeC_5": {},
    "BannerUdeC_6": {},
    "BannerUdeC_7": {},
    "Botones_atras_siguiente": {},
    "Botones_atras_siguiente_1": {},
    "Botones_atras_siguiente_2": {},
    "Botones_atras_siguiente_3": {},
    "Botones_atras_siguiente_4": {},
    "Botones_atras_siguiente_5": {},
    "Botones_atras_siguiente_6": {},
    "Botones_atras_siguiente_7": {},
    "btn_adjuntar_1": {},
    "btn_adjuntar_2": {},
    "btn_buscar_promotor": {},
    "btn_buscar_responsable": {},
    "btn_contraparte_in_popup_buscar": {},
    "btn_contraparte_in_popup_cancelar": {},
    "btn_contraparte_na_popup_buscar": {},
    "btn_contraparte_na_popup_cancelar": {},
    "btn_detalle_contraparte_nacional": {},
    "btn_detalle_contraparte_nacional_1": {},
    "btn_ods_1": {},
    "btn_ods_10": {},
    "btn_ods_11": {},
    "btn_ods_12": {},
    "btn_ods_13": {},
    "btn_ods_14": {},
    "btn_ods_15": {},
    "btn_ods_16": {},
    "btn_ods_17": {},
    "btn_ods_2": {},
    "btn_ods_3": {},
    "btn_ods_4": {},
    "btn_ods_5": {},
    "btn_ods_6": {},
    "btn_ods_7": {},
    "btn_ods_8": {},
    "btn_ods_9": {},
    "btn_promotor_popup_buscar": {},
    "btn_promotor_popup_cancelar": {},
    "btn_registro_10_politica": {},
    "btn_registro_10_popup_cancelar": {},
    "btn_registro_10_popup_cancelar_1": {},
    "btn_registro_10_popup_guardar": {},
    "btn_registro_10_popup_guardar_1": {},
    "btn_registro_11_agenda": {},
    "btn_registro_4_e_agregar": {},
    "btn_registro_5_popup_atras_1": {},
    "btn_registro_5_popup_enviar": {},
    "btn_responsable_popup_buscar": {},
    "btn_responsable_popup_cancelar": {},
    "buscador_a_t_input": {},
    "buscador_n_u_s_input": {},
    "buscar": {},
    "buscar_1": {},
    "buscar_2": {},
    "buscar_3": {},
    "buscar_4": {},
    "buscar_5": {},
    "Button1": {},
    "Cargo_autoridad_2": {},
    "cargo_autoridad_input_2": {},
    "cargo_autoridad_label_2": {},
    "Cargo_promotor_2": {},
    "cargo_promotor_input_2": {},
    "cargo_promotor_label_2": {},
    "Cargo_responsable_2": {},
    "cargo_responsable_input_2": {},
    "Cargo_responsable_institucional_in": {},
    "cargo_responsable_institucional_in_input": {},
    "cargo_responsable_institucional_in_label": {},
    "Cargo_responsable_institucional_na": {},
    "cargo_responsable_institucional_na_input": {},
    "cargo_responsable_institucional_na_label": {},
    "cargo_responsable_label_2": {},
    "cb_desarrollo_ambiental": {},
    "cb_desarrollo_cultural": {},
    "cb_desarrollo_productivo": {},
    "cb_desarrollo_social": {},
    "cb_educacion": {},
    "cb_formacion_investigacion": {},
    "cb_formacion_permanente": {},
    "cb_formacion_postgrado": {},
    "cb_formacion_pregrado": {},
    "cb_inclusion": {},
    "cb_interculturalidad": {},
    "cb_ods_1": {},
    "cb_ods_10": {},
    "cb_ods_11": {},
    "cb_ods_12": {},
    "cb_ods_13": {},
    "cb_ods_14": {},
    "cb_ods_15": {},
    "cb_ods_16": {},
    "cb_ods_17": {},
    "cb_ods_2": {},
    "cb_ods_3": {},
    "cb_ods_4": {},
    "cb_ods_5": {},
    "cb_ods_6": {},
    "cb_ods_7": {},
    "cb_ods_8": {},
    "cb_ods_9": {},
    "cb_ods_ninguno": {},
    "cb_patrimonio": {},
    "cb_salud": {},
    "cb_sector_publico": {},
    "cont_contraparte_internacional": {},
    "cont_contraparte_nacional": {},
    "cont_loading": {},
    "cont_loading_1": {},
    "cont_loading_2": {},
    "cont_loading_3": {},
    "cont_ods_1": {},
    "cont_ods_10": {},
    "cont_ods_11": {},
    "cont_ods_12": {},
    "cont_ods_13": {},
    "cont_ods_14": {},
    "cont_ods_15": {},
    "cont_ods_16": {},
    "cont_ods_17": {},
    "cont_ods_2": {},
    "cont_ods_3": {},
    "cont_ods_4": {},
    "cont_ods_5": {},
    "cont_ods_6": {},
    "cont_ods_7": {},
    "cont_ods_8": {},
    "cont_ods_9": {},
    "cont_ods_ninguno": {},
    "cont_vacio_in": {},
    "cont_vacio_na": {},
    "Contenedor_a_d_c": {},
    "Contenedor_a_d_p": {},
    "Contenedor_a_t": {},
    "Contenedor_c_d_s": {},
    "Contenedor_c_d_t": {},
    "Contenedor_casilla": {},
    "Contenedor_casilla_1": {},
    "Contenedor_casilla_10": {},
    "Contenedor_casilla_11": {},
    "Contenedor_casilla_12": {},
    "Contenedor_casilla_13": {},
    "Contenedor_casilla_2": {},
    "Contenedor_casilla_3": {},
    "Contenedor_casilla_4": {},
    "Contenedor_casilla_5": {},
    "Contenedor_casilla_6": {},
    "Contenedor_casilla_7": {},
    "Contenedor_casilla_8": {},
    "Contenedor_casilla_9": {},
    "Contenedor_d_c_s": {},
    "Contenedor_d_e_c_in": {},
    "Contenedor_d_e_c_na": {},
    "Contenedor_d_i_c": {},
    "Contenedor_d_u_s_op3": {},
    "Contenedor_datos_convenio": {},
    "Contenedor_e_c": {},
    "Contenedor_m_c": {},
    "Contenedor_s_d_p": {},
    "Contenedor_seleccionable": {},
    "Contenedor_seleccionable_1": {},
    "Contenedor_seleccionable_4": {},
    "Contenedor_seleccionable_5": {},
    "Contenedor_seleccionable_6": {},
    "Contenedor_seleccionable_7": {},
    "Contenedor_seleccionable_tipo_solicitud": {},
    "Contenedor_seleccionable_tipología": {},
    "Contenedor_t_c": {},
    "Contenedor_t_s": {},
    "contraparte_internacional_popup": {},
    "contraparte_nacional_popup": {},
    "contribución_al_desarrollo": {},
    "Contribución_al_desarrollo": {},
    "Contribución_desarrollo": {},
    "convenio_de_tipo": {},
    "convenio_tipo": {},
    "Correo_autoridad_2": {},
    "correo_autoridad_input_2": {},
    "correo_autoridad_label_2": {},
    "correo_electronico_in": {},
    "correo_electronico_in_input": {},
    "correo_electronico_in_label": {},
    "correo_electronico_na": {},
    "correo_electronico_na_input": {},
    "correo_electronico_na_label": {},
    "Correo_promotor_2": {},
    "correo_promotor_input_2": {},
    "correo_promotor_label_2": {},
    "Correo_responsable_2": {},
    "correo_responsable_input_2": {},
    "correo_responsable_label_2": {},
    "Datos_contraparte_internacional": {},
    "Datos_contraparte_nacional": {},
    "Datos_convenio": {},
    "datos_convenio_solicitado": {},
    "datos_de_la_unidad_1": {},
    "datos_del_promotor_1": {},
    "datos_del_responsable_1": {},
    "datos_entidad_contraparte_in": {},
    "Datos_entidad_contraparte_in": {},
    "datos_entidad_contraparte_na": {},
    "Datos_entidad_contraparte_na": {},
    "datos_info_convenio": {},
    "Datos_unidad_solicitante": {},
    "datos_unidad_solicitante_3": {},
    "descripcion_proposito_1": {},
    "documentacion": {},
    "Documentacion": {},
    "Eliminar": {},
    "Eliminar_1": {},
    "Entidad_contraparte": {},
    "entidades_contraparte": {},
    "Entidades_contraparte": {},
    "Especificaciones_convenio": {},
    "fig_background_perfil": {},
    "fig_contraparte_arrow": {},
    "fig_contraparte_arrow_1": {},
    "fig_registro_10_popup_bg": {},
    "fig_registro_10_popup_bg_1": {},
    "fig_registro_5_bg": {},
    "fig_registro_5_bg_1": {},
    "fig_registro_5_bg_2": {},
    "fig_registro_5_bg_3": {},
    "fig_registro_5_popup_bg": {},
    "fig_registro_5_popup_bg_1": {},
    "fig_registro_5_popup_bg_2": {},
    "fig_registro_5_popup_bg_3": {},
    "fig_registro_5_popup_bg_4": {},
    "fondo_blanco": {},
    "fondo_blanco_1": {},
    "fondo_blanco_10": {},
    "fondo_blanco_11": {},
    "fondo_blanco_12": {},
    "fondo_blanco_3": {},
    "fondo_blanco_4": {},
    "fondo_blanco_5": {},
    "fondo_blanco_6": {},
    "fondo_blanco_7": {},
    "fondo_blanco_8": {},
    "fondo_blanco_9": {},
    "fondo_celeste": {},
    "fondo_celeste_1": {},
    "fondo_celeste_10": {},
    "fondo_celeste_11": {},
    "fondo_celeste_2": {},
    "fondo_celeste_3": {},
    "fondo_celeste_8": {},
    "fondo_celeste_9": {},
    "fondo_registro_1": {},
    "fondo_registro_2": {},
    "gal_contraparte_internacional": {},
    "gal_contraparte_nacional": {},
    "gal_tabs": {},
    "Gallery1_1": {},
    "Gallery1_2": {},
    "galleryTemplate1_1": {},
    "galleryTemplate1_2": {},
    "galleryTemplate1_3": {},
    "galleryTemplate1_4": {},
    "galleryTemplate2": {},
    "grp_registro_5_popup_1": {},
    "Guardar": {},
    "Guardar_1": {},
    "HeaderUdeC": {},
    "Host": {},
    "icon_tabs_contenido_separador": {},
    "Image1": {},
    "Image1_1": {},
    "img_arrow_contraparte_nacional": {},
    "img_arrow_contraparte_nacional_1": {},
    "img_contraparte": {},
    "img_contraparte_1": {},
    "img_info_ods_1": {},
    "img_info_ods_10": {},
    "img_info_ods_11": {},
    "img_info_ods_12": {},
    "img_info_ods_13": {},
    "img_info_ods_14": {},
    "img_info_ods_15": {},
    "img_info_ods_16": {},
    "img_info_ods_17": {},
    "img_info_ods_2": {},
    "img_info_ods_3": {},
    "img_info_ods_4": {},
    "img_info_ods_5": {},
    "img_info_ods_6": {},
    "img_info_ods_7": {},
    "img_info_ods_8": {},
    "img_info_ods_9": {},
    "img_loading": {},
    "img_loading_1": {},
    "img_loading_2": {},
    "img_loading_3": {},
    "img_logo_udec": {},
    "img_ods_1": {},
    "img_ods_10": {},
    "img_ods_11": {},
    "img_ods_12": {},
    "img_ods_13": {},
    "img_ods_14": {},
    "img_ods_15": {},
    "img_ods_16": {},
    "img_ods_17": {},
    "img_ods_18": {},
    "img_ods_2": {},
    "img_ods_3": {},
    "img_ods_4": {},
    "img_ods_5": {},
    "img_ods_6": {},
    "img_ods_7": {},
    "img_ods_8": {},
    "img_ods_9": {},
    "img_perfil": {},
    "img_registro_10_popup": {},
    "img_registro_10_popup_1": {},
    "img_registro_10_popup_bg": {},
    "img_registro_10_popup_bg_1": {},
    "img_registro_5_popup_bg_1": {},
    "img_subir_1": {},
    "img_subir_2": {},
    "Información_convenio": {},
    "Información_de_convenio": {},
    "inp_contraparte_in_popup_search": {},
    "inp_contraparte_na_popup_search": {},
    "inp_promotor_popup_search": {},
    "inp_responsable_popup_search": {},
    "lbl_bienvenido": {},
    "lbl_contraparte_in_popup_faltandatos": {},
    "lbl_contraparte_in_popup_noencontrado": {},
    "lbl_contraparte_in_popup_rut": {},
    "lbl_contraparte_in_popup_titulo": {},
    "lbl_contraparte_na_popup_faltandatos": {},
    "lbl_contraparte_na_popup_noencontrado": {},
    "lbl_contraparte_na_popup_rut": {},
    "lbl_contraparte_na_popup_titulo": {},
    "lbl_contraparte_nacional_nombre": {},
    "lbl_contraparte_nacional_nombre_1": {},
    "lbl_contraparte_nacional_rut": {},
    "lbl_contraparte_nacional_rut_1": {},
    "lbl_educacion": {},
    "lbl_falta_correo": {},
    "lbl_falta_correo_1": {},
    "lbl_faltan_datos": {},
    "lbl_faltan_datos_1": {},
    "lbl_faltan_datos_2": {},
    "lbl_faltan_datos_3": {},
    "lbl_faltan_datos_4": {},
    "lbl_faltan_datos_5": {},
    "lbl_faltan_datos_6": {},
    "lbl_nombre_usuario": {},
    "lbl_promotor_popup_correo": {},
    "lbl_promotor_popup_faltandatos": {},
    "lbl_promotor_popup_noencontrado": {},
    "lbl_promotor_popup_titulo": {},
    "lbl_registro_10_faltandatos_1": {},
    "lbl_registro_10_faltandatos_2": {},
    "lbl_registro_10_popup_titulo": {},
    "lbl_registro_10_popup_titulo_1": {},
    "lbl_registro_9_desarrollo_ambiental": {},
    "lbl_registro_9_desarrollo_cultural": {},
    "lbl_registro_9_desarrollo_productivo": {},
    "lbl_registro_9_desarrollo_social": {},
    "lbl_registro_9_formacion_permanente": {},
    "lbl_registro_9_formacion_postgrado": {},
    "lbl_registro_9_formacion_pregrado": {},
    "lbl_registro_9_inclusion": {},
    "lbl_registro_9_interculturalidad": {},
    "lbl_registro_9_investigacion": {},
    "lbl_registro_9_patrimonio": {},
    "lbl_registro_9_salud": {},
    "lbl_registro_9_sector_publico": {},
    "lbl_registro_popup_5_correo_1": {},
    "lbl_registro_popup_5_titulo_1": {},
    "lbl_responsable_popup_correo": {},
    "lbl_responsable_popup_faltandatos": {},
    "lbl_responsable_popup_noencontrado": {},
    "lbl_responsable_popup_titulo": {},
    "lbl_subtitulo": {},
    "lbl_titulo": {},
    "modalidades": {},
    "no_contraparte_in_lb": {},
    "no_contraparte_na_lb": {},
    "Nombre_autoridad_2": {},
    "nombre_autoridad_solicitante_input_2": {},
    "nombre_autoridad_solicitante_label_2": {},
    "Nombre_promotor_2": {},
    "nombre_promotor_input_2": {},
    "nombre_promotor_label_2": {},
    "Nombre_representante_legal_in": {},
    "nombre_representante_legal_in_input": {},
    "nombre_representante_legal_in_label": {},
    "Nombre_representante_legal_na": {},
    "nombre_representante_legal_na_input": {},
    "nombre_representante_legal_na_label": {},
    "Nombre_responsable_2": {},
    "nombre_responsable_input_2": {},
    "Nombre_responsable_institucional_in": {},
    "nombre_responsable_institucional_in_input": {},
    "nombre_responsable_institucional_in_label": {},
    "Nombre_responsable_institucional_na": {},
    "nombre_responsable_institucional_na_input": {},
    "nombre_responsable_institucional_na_label": {},
    "nombre_responsable_label_2": {},
    "Nombre_unidad_contraparte_in": {},
    "nombre_unidad_contraparte_in_input": {},
    "nombre_unidad_contraparte_in_label": {},
    "Nombre_unidad_contraparte_na": {},
    "nombre_unidad_contraparte_na_input": {},
    "nombre_unidad_contraparte_na_label": {},
    "nombre_unidad_input": {},
    "nombre_unidad_input_3": {},
    "nombre_unidad_label_2": {},
    "nombre_unidad_solicitante": {},
    "Nombre_unidad_solicitante_2": {},
    "pais_in": {},
    "pais_in_input": {},
    "pais_in_label": {},
    "pais_na": {},
    "pais_na_input": {},
    "pais_na_label": {},
    "promotor_popup": {},
    "Promotor_unidad_2": {},
    "Promotor_unidad_solicitante_in": {},
    "Promotor_unidad_solicitante_na": {},
    "Propósito": {},
    "propósito_central": {},
    "Responsable_institucional_2": {},
    "responsable_popup": {},
    "sector_de_politica": {},
    "sector_politica": {},
    "separador": {},
    "separador_1": {},
    "Siguiente": {},
    "Siguiente_1": {},
    "Siguiente_2": {},
    "Siguiente_3": {},
    "Siguiente_4": {},
    "Siguiente_5": {},
    "Siguiente_6": {},
    "Siguiente_7": {},
    "sin_alcance_territorial": {},
    "sin_ambito_politica": {},
    "sin_cargo": {},
    "sin_cargo_in": {},
    "sin_cargo_promotor_1": {},
    "sin_cargo_responsable": {},
    "sin_contraparte_in_lb": {},
    "sin_contraparte_na_lb": {},
    "sin_convenio_tipo": {},
    "sin_correo_in": {},
    "sin_correo_na": {},
    "sin_correo_promotor": {},
    "sin_correo_responsable": {},
    "sin_documento_extra": {},
    "sin_documento_oficial": {},
    "sin_modalidad": {},
    "sin_nombre_promotor": {},
    "sin_nombre_representante_legal": {},
    "sin_nombre_representante_legal_in": {},
    "sin_nombre_responsable": {},
    "sin_nombre_responsable_institucional": {},
    "sin_nombre_responsable_institucional_in": {},
    "sin_nombre_unidad": {},
    "sin_proposito_central": {},
    "sin_sector_politica": {},
    "sin_solicitud": {},
    "sin_telefono_promotor": {},
    "sin_telefono_responsable": {},
    "sin_tipologia": {},
    "solicitud": {},
    "tapar_ambito_politica": {},
    "tapar_convenio_tipo": {},
    "tapar_convenio_tipo_1": {},
    "tapar_nombre_unidad_solicitante": {},
    "tapar_tipo_alcance": {},
    "tapar_tipo_modalidades": {},
    "tapar_tipo_solicitud": {},
    "tapar_tipo_tipologia": {},
    "Telefono_autoridad_2": {},
    "telefono_autoridad_input_2": {},
    "telefono_autoridad_label_2": {},
    "Telefono_promotor_2": {},
    "telefono_promotor_input_2": {},
    "telefono_promotor_label_2": {},
    "Telefono_responsable_2": {},
    "telefono_responsable_input_2": {},
    "telefono_responsable_label_2": {},
    "tipo_alcance": {},
    "tipo_modalidades": {},
    "tipo_solicitud": {},
    "tipo_tipologia": {},
    "tipologia": {},
    "Title1_1": {},
    "Title1_2": {},
    "Unidad_solicitante": {}
  },
  "PCFDynamicSchemaForIRRetrievalEntry": {},
  "PCFTemplateEntry": {},
  "PublishOrderIndices": {
    "a_d_c_e": 370,
    "a_d_c_i": 356,
    "Adjuntar_documento_extra": 168,
    "adjuntar_documento_label_1": 160,
    "adjuntar_documento_label_2": 169,
    "Adjuntar_documento_oficial": 159,
    "Adjuntar_popup_extra": 109,
    "Adjuntar_popup_oficial": 99,
    "alcance_territorial": 125,
    "alcance_territorial_convenio_solicitado": 123,
    "alcance_territorial_convenio_solicitado_1": 323,
    "ambito_de_politica": 339,
    "ambito_politica": 345,
    "App": 0,
    "Area_contribución": 0,
    "area_contribución_externa": 371,
    "area_contribución_interna": 357,
    "area_de_contribución": 353,
    "Area_de_contribución": 352,
    "Atrás": 97,
    "Atrás_1": 179,
    "Atrás_2": 218,
    "Atrás_3": 265,
    "Atrás_4": 314,
    "Atrás_5": 349,
    "Atrás_6": 404,
    "Atrás_7": 512,
    "att_registro_10_attach_extra": 114,
    "att_registro_10_attach_oficial": 104,
    "Autoridad_solicitante_2": 45,
    "BannerUdeC": 0,
    "BannerUdeC_1": 108,
    "BannerUdeC_2": 181,
    "BannerUdeC_3": 220,
    "BannerUdeC_4": 269,
    "BannerUdeC_5": 318,
    "BannerUdeC_6": 351,
    "BannerUdeC_7": 406,
    "Botones_atras_siguiente": 96,
    "Botones_atras_siguiente_1": 178,
    "Botones_atras_siguiente_2": 217,
    "Botones_atras_siguiente_3": 264,
    "Botones_atras_siguiente_4": 313,
    "Botones_atras_siguiente_5": 348,
    "Botones_atras_siguiente_6": 403,
    "Botones_atras_siguiente_7": 511,
    "btn_adjuntar_1": 167,
    "btn_adjuntar_2": 176,
    "btn_buscar_promotor": 41,
    "btn_buscar_responsable": 42,
    "btn_contraparte_in_popup_buscar": 280,
    "btn_contraparte_in_popup_cancelar": 279,
    "btn_contraparte_na_popup_buscar": 231,
    "btn_contraparte_na_popup_cancelar": 230,
    "btn_detalle_contraparte_nacional": 201,
    "btn_detalle_contraparte_nacional_1": 192,
    "btn_ods_1": 420,
    "btn_ods_10": 465,
    "btn_ods_11": 470,
    "btn_ods_12": 475,
    "btn_ods_13": 480,
    "btn_ods_14": 485,
    "btn_ods_15": 490,
    "btn_ods_16": 495,
    "btn_ods_17": 500,
    "btn_ods_2": 425,
    "btn_ods_3": 430,
    "btn_ods_4": 435,
    "btn_ods_5": 440,
    "btn_ods_6": 445,
    "btn_ods_7": 450,
    "btn_ods_8": 455,
    "btn_ods_9": 460,
    "btn_promotor_popup_buscar": 11,
    "btn_promotor_popup_cancelar": 10,
    "btn_registro_10_politica": 346,
    "btn_registro_10_popup_cancelar": 106,
    "btn_registro_10_popup_cancelar_1": 116,
    "btn_registro_10_popup_guardar": 107,
    "btn_registro_10_popup_guardar_1": 117,
    "btn_registro_11_agenda": 413,
    "btn_registro_4_e_agregar": 216,
    "btn_registro_5_popup_atras_1": 508,
    "btn_registro_5_popup_enviar": 509,
    "btn_responsable_popup_buscar": 23,
    "btn_responsable_popup_cancelar": 22,
    "buscador_a_t_input": 128,
    "buscador_n_u_s_input": 34,
    "buscar": 7,
    "buscar_1": 43,
    "buscar_2": 19,
    "buscar_3": 44,
    "buscar_4": 227,
    "buscar_5": 276,
    "Button1": 188,
    "Cargo_autoridad_2": 49,
    "cargo_autoridad_input_2": 51,
    "cargo_autoridad_label_2": 50,
    "Cargo_promotor_2": 64,
    "cargo_promotor_input_2": 67,
    "cargo_promotor_label_2": 65,
    "Cargo_responsable_2": 82,
    "cargo_responsable_input_2": 85,
    "Cargo_responsable_institucional_in": 299,
    "cargo_responsable_institucional_in_input": 301,
    "cargo_responsable_institucional_in_label": 300,
    "Cargo_responsable_institucional_na": 250,
    "cargo_responsable_institucional_na_input": 252,
    "cargo_responsable_institucional_na_label": 251,
    "cargo_responsable_label_2": 83,
    "cb_desarrollo_ambiental": 373,
    "cb_desarrollo_cultural": 388,
    "cb_desarrollo_productivo": 379,
    "cb_desarrollo_social": 385,
    "cb_educacion": 391,
    "cb_formacion_investigacion": 368,
    "cb_formacion_permanente": 362,
    "cb_formacion_postgrado": 365,
    "cb_formacion_pregrado": 359,
    "cb_inclusion": 397,
    "cb_interculturalidad": 394,
    "cb_ods_1": 417,
    "cb_ods_10": 462,
    "cb_ods_11": 467,
    "cb_ods_12": 472,
    "cb_ods_13": 477,
    "cb_ods_14": 482,
    "cb_ods_15": 487,
    "cb_ods_16": 492,
    "cb_ods_17": 497,
    "cb_ods_2": 422,
    "cb_ods_3": 427,
    "cb_ods_4": 432,
    "cb_ods_5": 437,
    "cb_ods_6": 442,
    "cb_ods_7": 447,
    "cb_ods_8": 452,
    "cb_ods_9": 457,
    "cb_ods_ninguno": 502,
    "cb_patrimonio": 382,
    "cb_salud": 400,
    "cb_sector_publico": 376,
    "cont_contraparte_internacional": 189,
    "cont_contraparte_nacional": 198,
    "cont_loading": 24,
    "cont_loading_1": 233,
    "cont_loading_2": 282,
    "cont_loading_3": 410,
    "cont_ods_1": 416,
    "cont_ods_10": 461,
    "cont_ods_11": 466,
    "cont_ods_12": 471,
    "cont_ods_13": 476,
    "cont_ods_14": 481,
    "cont_ods_15": 486,
    "cont_ods_16": 491,
    "cont_ods_17": 496,
    "cont_ods_2": 421,
    "cont_ods_3": 426,
    "cont_ods_4": 431,
    "cont_ods_5": 436,
    "cont_ods_6": 441,
    "cont_ods_7": 446,
    "cont_ods_8": 451,
    "cont_ods_9": 456,
    "cont_ods_ninguno": 501,
    "cont_vacio_in": 211,
    "cont_vacio_na": 207,
    "Contenedor_a_d_c": 354,
    "Contenedor_a_d_p": 338,
    "Contenedor_a_t": 124,
    "Contenedor_c_d_s": 414,
    "Contenedor_c_d_t": 324,
    "Contenedor_casilla": 358,
    "Contenedor_casilla_1": 364,
    "Contenedor_casilla_10": 375,
    "Contenedor_casilla_11": 381,
    "Contenedor_casilla_12": 387,
    "Contenedor_casilla_13": 393,
    "Contenedor_casilla_2": 367,
    "Contenedor_casilla_3": 361,
    "Contenedor_casilla_4": 372,
    "Contenedor_casilla_5": 378,
    "Contenedor_casilla_6": 384,
    "Contenedor_casilla_7": 390,
    "Contenedor_casilla_8": 396,
    "Contenedor_casilla_9": 399,
    "Contenedor_d_c_s": 120,
    "Contenedor_d_e_c_in": 285,
    "Contenedor_d_e_c_na": 236,
    "Contenedor_d_i_c": 321,
    "Contenedor_d_u_s_op3": 27,
    "Contenedor_datos_convenio": 118,
    "Contenedor_e_c": 184,
    "Contenedor_m_c": 146,
    "Contenedor_s_d_p": 331,
    "Contenedor_seleccionable": 148,
    "Contenedor_seleccionable_1": 126,
    "Contenedor_seleccionable_4": 32,
    "Contenedor_seleccionable_5": 326,
    "Contenedor_seleccionable_6": 341,
    "Contenedor_seleccionable_7": 333,
    "Contenedor_seleccionable_tipo_solicitud": 141,
    "Contenedor_seleccionable_tipología": 134,
    "Contenedor_t_c": 132,
    "Contenedor_t_s": 139,
    "contraparte_internacional_popup": 270,
    "contraparte_nacional_popup": 221,
    "contribución_al_desarrollo": 412,
    "Contribución_al_desarrollo": 411,
    "Contribución_desarrollo": 0,
    "convenio_de_tipo": 325,
    "convenio_tipo": 330,
    "Correo_autoridad_2": 52,
    "correo_autoridad_input_2": 54,
    "correo_autoridad_label_2": 53,
    "correo_electronico_in": 306,
    "correo_electronico_in_input": 308,
    "correo_electronico_in_label": 307,
    "correo_electronico_na": 257,
    "correo_electronico_na_input": 259,
    "correo_electronico_na_label": 258,
    "Correo_promotor_2": 68,
    "correo_promotor_input_2": 71,
    "correo_promotor_label_2": 69,
    "Correo_responsable_2": 86,
    "correo_responsable_input_2": 89,
    "correo_responsable_label_2": 87,
    "Datos_contraparte_internacional": 0,
    "Datos_contraparte_nacional": 0,
    "Datos_convenio": 0,
    "datos_convenio_solicitado": 119,
    "datos_de_la_unidad_1": 38,
    "datos_del_promotor_1": 39,
    "datos_del_responsable_1": 40,
    "datos_entidad_contraparte_in": 284,
    "Datos_entidad_contraparte_in": 283,
    "datos_entidad_contraparte_na": 235,
    "Datos_entidad_contraparte_na": 234,
    "datos_info_convenio": 320,
    "Datos_unidad_solicitante": 25,
    "datos_unidad_solicitante_3": 26,
    "descripcion_proposito_1": 156,
    "documentacion": 158,
    "Documentacion": 157,
    "Eliminar": 266,
    "Eliminar_1": 315,
    "Entidad_contraparte": 0,
    "entidades_contraparte": 183,
    "Entidades_contraparte": 182,
    "Especificaciones_convenio": 122,
    "fig_background_perfil": 516,
    "fig_contraparte_arrow": 206,
    "fig_contraparte_arrow_1": 197,
    "fig_registro_10_popup_bg": 100,
    "fig_registro_10_popup_bg_1": 110,
    "fig_registro_5_bg": 12,
    "fig_registro_5_bg_1": 232,
    "fig_registro_5_bg_2": 281,
    "fig_registro_5_bg_3": 408,
    "fig_registro_5_popup_bg": 2,
    "fig_registro_5_popup_bg_1": 14,
    "fig_registro_5_popup_bg_2": 222,
    "fig_registro_5_popup_bg_3": 271,
    "fig_registro_5_popup_bg_4": 407,
    "fondo_blanco": 3,
    "fondo_blanco_1": 121,
    "fondo_blanco_10": 355,
    "fondo_blanco_11": 28,
    "fondo_blanco_12": 415,
    "fondo_blanco_3": 15,
    "fondo_blanco_4": 223,
    "fondo_blanco_5": 185,
    "fondo_blanco_6": 237,
    "fondo_blanco_7": 286,
    "fondo_blanco_8": 272,
    "fondo_blanco_9": 322,
    "fondo_celeste": 149,
    "fondo_celeste_1": 135,
    "fondo_celeste_10": 342,
    "fondo_celeste_11": 334,
    "fondo_celeste_2": 127,
    "fondo_celeste_3": 142,
    "fondo_celeste_8": 33,
    "fondo_celeste_9": 328,
    "fondo_registro_1": 162,
    "fondo_registro_2": 171,
    "gal_contraparte_internacional": 190,
    "gal_contraparte_nacional": 199,
    "gal_tabs": 186,
    "Gallery1_1": 163,
    "Gallery1_2": 172,
    "galleryTemplate1_1": 164,
    "galleryTemplate1_2": 200,
    "galleryTemplate1_3": 173,
    "galleryTemplate1_4": 191,
    "galleryTemplate2": 187,
    "grp_registro_5_popup_1": 409,
    "Guardar": 268,
    "Guardar_1": 317,
    "HeaderUdeC": 0,
    "Host": 0,
    "icon_tabs_contenido_separador": 215,
    "Image1": 208,
    "Image1_1": 212,
    "img_arrow_contraparte_nacional": 204,
    "img_arrow_contraparte_nacional_1": 195,
    "img_contraparte": 203,
    "img_contraparte_1": 194,
    "img_info_ods_1": 419,
    "img_info_ods_10": 464,
    "img_info_ods_11": 469,
    "img_info_ods_12": 474,
    "img_info_ods_13": 479,
    "img_info_ods_14": 484,
    "img_info_ods_15": 489,
    "img_info_ods_16": 494,
    "img_info_ods_17": 499,
    "img_info_ods_2": 424,
    "img_info_ods_3": 429,
    "img_info_ods_4": 434,
    "img_info_ods_5": 439,
    "img_info_ods_6": 444,
    "img_info_ods_7": 449,
    "img_info_ods_8": 454,
    "img_info_ods_9": 459,
    "img_loading": 94,
    "img_loading_1": 261,
    "img_loading_2": 310,
    "img_loading_3": 506,
    "img_logo_udec": 518,
    "img_ods_1": 418,
    "img_ods_10": 463,
    "img_ods_11": 468,
    "img_ods_12": 473,
    "img_ods_13": 478,
    "img_ods_14": 483,
    "img_ods_15": 488,
    "img_ods_16": 493,
    "img_ods_17": 498,
    "img_ods_18": 503,
    "img_ods_2": 423,
    "img_ods_3": 428,
    "img_ods_4": 433,
    "img_ods_5": 438,
    "img_ods_6": 443,
    "img_ods_7": 448,
    "img_ods_8": 453,
    "img_ods_9": 458,
    "img_perfil": 517,
    "img_registro_10_popup": 103,
    "img_registro_10_popup_1": 113,
    "img_registro_10_popup_bg": 101,
    "img_registro_10_popup_bg_1": 111,
    "img_registro_5_popup_bg_1": 504,
    "img_subir_1": 166,
    "img_subir_2": 175,
    "Información_convenio": 0,
    "Información_de_convenio": 319,
    "inp_contraparte_in_popup_search": 275,
    "inp_contraparte_na_popup_search": 226,
    "inp_promotor_popup_search": 6,
    "inp_responsable_popup_search": 18,
    "lbl_bienvenido": 515,
    "lbl_contraparte_in_popup_faltandatos": 277,
    "lbl_contraparte_in_popup_noencontrado": 278,
    "lbl_contraparte_in_popup_rut": 274,
    "lbl_contraparte_in_popup_titulo": 273,
    "lbl_contraparte_na_popup_faltandatos": 228,
    "lbl_contraparte_na_popup_noencontrado": 229,
    "lbl_contraparte_na_popup_rut": 225,
    "lbl_contraparte_na_popup_titulo": 224,
    "lbl_contraparte_nacional_nombre": 202,
    "lbl_contraparte_nacional_nombre_1": 193,
    "lbl_contraparte_nacional_rut": 205,
    "lbl_contraparte_nacional_rut_1": 196,
    "lbl_educacion": 392,
    "lbl_falta_correo": 262,
    "lbl_falta_correo_1": 311,
    "lbl_faltan_datos": 95,
    "lbl_faltan_datos_1": 177,
    "lbl_faltan_datos_2": 263,
    "lbl_faltan_datos_3": 312,
    "lbl_faltan_datos_4": 347,
    "lbl_faltan_datos_5": 402,
    "lbl_faltan_datos_6": 510,
    "lbl_nombre_usuario": 519,
    "lbl_promotor_popup_correo": 5,
    "lbl_promotor_popup_faltandatos": 8,
    "lbl_promotor_popup_noencontrado": 9,
    "lbl_promotor_popup_titulo": 4,
    "lbl_registro_10_faltandatos_1": 105,
    "lbl_registro_10_faltandatos_2": 115,
    "lbl_registro_10_popup_titulo": 102,
    "lbl_registro_10_popup_titulo_1": 112,
    "lbl_registro_9_desarrollo_ambiental": 374,
    "lbl_registro_9_desarrollo_cultural": 389,
    "lbl_registro_9_desarrollo_productivo": 380,
    "lbl_registro_9_desarrollo_social": 386,
    "lbl_registro_9_formacion_permanente": 363,
    "lbl_registro_9_formacion_postgrado": 366,
    "lbl_registro_9_formacion_pregrado": 360,
    "lbl_registro_9_inclusion": 398,
    "lbl_registro_9_interculturalidad": 395,
    "lbl_registro_9_investigacion": 369,
    "lbl_registro_9_patrimonio": 383,
    "lbl_registro_9_salud": 401,
    "lbl_registro_9_sector_publico": 377,
    "lbl_registro_popup_5_correo_1": 507,
    "lbl_registro_popup_5_titulo_1": 505,
    "lbl_responsable_popup_correo": 17,
    "lbl_responsable_popup_faltandatos": 20,
    "lbl_responsable_popup_noencontrado": 21,
    "lbl_responsable_popup_titulo": 16,
    "lbl_subtitulo": 520,
    "lbl_titulo": 514,
    "modalidades": 147,
    "no_contraparte_in_lb": 214,
    "no_contraparte_na_lb": 210,
    "Nombre_autoridad_2": 46,
    "nombre_autoridad_solicitante_input_2": 48,
    "nombre_autoridad_solicitante_label_2": 47,
    "Nombre_promotor_2": 60,
    "nombre_promotor_input_2": 63,
    "nombre_promotor_label_2": 61,
    "Nombre_representante_legal_in": 290,
    "nombre_representante_legal_in_input": 292,
    "nombre_representante_legal_in_label": 291,
    "Nombre_representante_legal_na": 241,
    "nombre_representante_legal_na_input": 243,
    "nombre_representante_legal_na_label": 242,
    "Nombre_responsable_2": 78,
    "nombre_responsable_input_2": 81,
    "Nombre_responsable_institucional_in": 295,
    "nombre_responsable_institucional_in_input": 297,
    "nombre_responsable_institucional_in_label": 296,
    "Nombre_responsable_institucional_na": 246,
    "nombre_responsable_institucional_na_input": 248,
    "nombre_responsable_institucional_na_label": 247,
    "nombre_responsable_label_2": 79,
    "Nombre_unidad_contraparte_in": 287,
    "nombre_unidad_contraparte_in_input": 289,
    "nombre_unidad_contraparte_in_label": 288,
    "Nombre_unidad_contraparte_na": 238,
    "nombre_unidad_contraparte_na_input": 240,
    "nombre_unidad_contraparte_na_label": 239,
    "nombre_unidad_input": 31,
    "nombre_unidad_input_3": 340,
    "nombre_unidad_label_2": 30,
    "nombre_unidad_solicitante": 37,
    "Nombre_unidad_solicitante_2": 29,
    "pais_in": 303,
    "pais_in_input": 305,
    "pais_in_label": 304,
    "pais_na": 254,
    "pais_na_input": 256,
    "pais_na_label": 255,
    "promotor_popup": 1,
    "Promotor_unidad_2": 59,
    "Promotor_unidad_solicitante_in": 294,
    "Promotor_unidad_solicitante_na": 245,
    "Propósito": 153,
    "propósito_central": 154,
    "Responsable_institucional_2": 77,
    "responsable_popup": 13,
    "sector_de_politica": 332,
    "sector_politica": 337,
    "separador": 58,
    "separador_1": 76,
    "Siguiente": 98,
    "Siguiente_1": 180,
    "Siguiente_2": 219,
    "Siguiente_3": 267,
    "Siguiente_4": 316,
    "Siguiente_5": 350,
    "Siguiente_6": 405,
    "Siguiente_7": 513,
    "sin_alcance_territorial": 130,
    "sin_ambito_politica": 343,
    "sin_cargo": 253,
    "sin_cargo_in": 302,
    "sin_cargo_promotor_1": 66,
    "sin_cargo_responsable": 84,
    "sin_contraparte_in_lb": 213,
    "sin_contraparte_na_lb": 209,
    "sin_convenio_tipo": 327,
    "sin_correo_in": 309,
    "sin_correo_na": 260,
    "sin_correo_promotor": 70,
    "sin_correo_responsable": 88,
    "sin_documento_extra": 170,
    "sin_documento_oficial": 161,
    "sin_modalidad": 151,
    "sin_nombre_promotor": 62,
    "sin_nombre_representante_legal": 244,
    "sin_nombre_representante_legal_in": 293,
    "sin_nombre_responsable": 80,
    "sin_nombre_responsable_institucional": 249,
    "sin_nombre_responsable_institucional_in": 298,
    "sin_nombre_unidad": 36,
    "sin_proposito_central": 155,
    "sin_sector_politica": 336,
    "sin_solicitud": 144,
    "sin_telefono_promotor": 74,
    "sin_telefono_responsable": 92,
    "sin_tipologia": 137,
    "solicitud": 140,
    "tapar_ambito_politica": 344,
    "tapar_convenio_tipo": 329,
    "tapar_convenio_tipo_1": 335,
    "tapar_nombre_unidad_solicitante": 35,
    "tapar_tipo_alcance": 129,
    "tapar_tipo_modalidades": 150,
    "tapar_tipo_solicitud": 143,
    "tapar_tipo_tipologia": 136,
    "Telefono_autoridad_2": 55,
    "telefono_autoridad_input_2": 57,
    "telefono_autoridad_label_2": 56,
    "Telefono_promotor_2": 72,
    "telefono_promotor_input_2": 75,
    "telefono_promotor_label_2": 73,
    "Telefono_responsable_2": 90,
    "telefono_responsable_input_2": 93,
    "telefono_responsable_label_2": 91,
    "tipo_alcance": 131,
    "tipo_modalidades": 152,
    "tipo_solicitud": 145,
    "tipo_tipologia": 138,
    "tipologia": 133,
    "Title1_1": 165,
    "Title1_2": 174,
    "Unidad_solicitante": 0
  },
  "ResourcesJsonIndices": {
    "Image-0": 12,
    "Image-1": 13,
    "Image-10": 22,
    "Image-11": 23,
    "Image-12": 24,
    "Image-13": 25,
    "Image-14": 26,
    "Image-15": 27,
    "Image-16": 28,
    "Image-17": 29,
    "Image-2": 14,
    "Image-3": 15,
    "Image-4": 16,
    "Image-5": 17,
    "Image-6": 18,
    "Image-7": 19,
    "Image-8": 20,
    "Image-9": 21,
    "Image-attach": 7,
    "Image-background-input": 3,
    "Image-background-section": 4,
    "Image-fondo_deshabilitado": 5,
    "Image-group-2-copy": 2,
    "Image-ico_arrow": 10,
    "Image-ico_search": 8,
    "Image-informacion": 30,
    "Image-loading": 9,
    "Image-logo-udec": 0,
    "Image-SampleImage": 1,
    "Image-upload": 6,
    "Image-vacio": 11
  },
  "RuleScreenIdWithoutScreen": {},
  "TemplateVersions": {},
  "VolatileProperties": {
    "AnalysisLoadTime": 2.0606246,
    "ControlCount": {
      "561f66e7d0a2482e9212edb43132f4a8": 9,
      "attachments": 2,
      "button": 61,
      "checkbox": 32,
      "circle": 1,
      "dropdown": 8,
      "gallery": 5,
      "galleryTemplate": 5,
      "group": 5,
      "groupContainer": 118,
      "icon": 1,
      "image": 82,
      "label": 110,
      "rectangle": 23,
      "screen": 8,
      "text": 60
    },
    "DeserializationLoadTime": 6.8580705,
    "ErrorCount": 0
  },
  "WasLocalDatabaseReferencesEmpty": true
}